robot_pt/__init__.py
robot_pt/__main__.py
robot_pt/action_decision_pt.py
robot_pt/action_reply_pt.py
robot_pt/state_description_pt.py
robot_pt/system_msg_pt.py
mol_robot_prompt_templates-0.0.5.dist-info/LICENSE
mol_robot_prompt_templates-0.0.5.dist-info/METADATA
mol_robot_prompt_templates-0.0.5.dist-info/WHEEL
mol_robot_prompt_templates-0.0.5.dist-info/entry_points.txt
mol_robot_prompt_templates-0.0.5.dist-info/top_level.txt
mol_robot_prompt_templates-0.0.5.dist-info/RECORD
