Metadata-Version: 2.1
Name: mol_robot_prompt_templates
Version: 0.0.5
Summary: Importable prompt templates for the MoL robot
Author-email: Robin Karlsson <robin.karlsson0@gmail.com>
License: GNU GENERAL PUBLIC LICENSE
Project-URL: Homepage, https://github.com/robin-karlsson0/robot_prompt_templates
Classifier: License :: OSI Approved :: GNU General Public License v3 (GPLv3)
Classifier: Programming Language :: Python
Classifier: Programming Language :: Python :: 3
Requires-Python: >=3.9
License-File: LICENSE
Provides-Extra: dev
Requires-Dist: black; extra == "dev"
Requires-Dist: bumpver; extra == "dev"
Requires-Dist: isort; extra == "dev"
Requires-Dist: pip-tools; extra == "dev"
Requires-Dist: pytest; extra == "dev"
